{"c2idx": {"ApplyMaterialPropertiesForElems": 0, "CalcEnergyForElems": 1, "CalcFBHourglassForceForElems": 2, "CalcForceForNodes": 3, "CalcHourglassControlForElems": 4, "CalcKinematicsForElems": 5, "CalcLagrangeElements": 6, "CalcMonotonicQForElems": 7, "CalcQForElems": 8, "CalcTimeConstraintsForElems": 9, "CalcVolumeForceForElems": 10, "EvalEOSForElems": 11, "IntegrateStressForElems": 12, "LagrangeElements": 13, "LagrangeLeapFrog": 14, "LagrangeNodal": 15, "TimeIncrement": 16, "main": 17, "null": -1}, "m2idx": {"main": 0, "LagrangeLeapFrog": 1, "CalcTimeConstraintsForElems": 2, "LagrangeElements": 3, "ApplyMaterialPropertiesForElems": 4, "EvalEOSForElems": 5, "CalcEnergyForElems": 6, "CalcLagrangeElements": 7, "CalcKinematicsForElems": 8, "CalcQForElems": 9, "CalcMonotonicQForElems": 10, "LagrangeNodal": 11, "CalcForceForNodes": 12, "CalcVolumeForceForElems": 13, "CalcHourglassControlForElems": 14, "CalcFBHourglassForceForElems": 15, "IntegrateStressForElems": 16, "TimeIncrement": 17, "null": -1}, "m2c": {"0": [17], "1": [14], "2": [9], "3": [13], "4": [0], "5": [11], "6": [1], "7": [6], "8": [5], "9": [8], "10": [7], "11": [15], "12": [3], "13": [10], "14": [4], "15": [2], "16": [12], "17": [16], "-1": []}}